Metadata-Version: 2.4
Name: mdx2
Version: 1.0.3
Summary: Macromolecular diffuse scattering data reduction
Author-email: Steve Meisburger <spm82@cornell.edu>
License-Expression: MIT
Project-URL: Homepage, https://github.com/ando-lab/mdx2
Project-URL: Issues, https://github.com/ando-lab/mdx2/issues
Classifier: Programming Language :: Python :: 3
Classifier: Operating System :: OS Independent
Requires-Python: >=3.9
License-File: LICENSE
Requires-Dist: numpy
Requires-Dist: pandas
Requires-Dist: scipy
Requires-Dist: dxtbx
Requires-Dist: nexusformat
Requires-Dist: joblib
Requires-Dist: numexpr
Requires-Dist: simple-parsing
Requires-Dist: loguru
Provides-Extra: test
Requires-Dist: pytest>=6.0; extra == "test"
Provides-Extra: dev
Requires-Dist: ruff>=0.1.0; extra == "dev"
Requires-Dist: pytest>=6.0; extra == "dev"
Dynamic: license-file
